pys3uploader/__init__.py
pys3uploader/exceptions.py
pys3uploader/logger.py
pys3uploader/metadata.py
pys3uploader/progress.py
pys3uploader/timer.py
pys3uploader/tree.py
pys3uploader/uploader.py
pys3uploader/utils.py
pys3uploader/version.py
pys3uploader-0.4.2.dist-info/LICENSE
pys3uploader-0.4.2.dist-info/METADATA
pys3uploader-0.4.2.dist-info/WHEEL
pys3uploader-0.4.2.dist-info/top_level.txt
pys3uploader-0.4.2.dist-info/RECORD
