Metadata-Version: 2.2
Name: PyS3Uploader
Version: 0.4.2
Summary: Python module to upload objects to an S3 bucket.
Author-email: Vignesh Rao <svignesh1793@gmail.com>
License: MIT License
Project-URL: Homepage, https://github.com/thevickypedia/PyS3Uploader
Project-URL: Docs, https://thevickypedia.github.io/PyS3Uploader/
Project-URL: Source, https://github.com/thevickypedia/PyS3Uploader
Project-URL: Bug Tracker, https://github.com/thevickypedia/PyS3Uploader/issues
Keywords: pys3uploader
Classifier: Development Status :: 1 - Planning
Classifier: Intended Audience :: Information Technology
Classifier: Operating System :: OS Independent
Classifier: License :: OSI Approved :: MIT License
Classifier: Programming Language :: Python :: 3.11
Classifier: Topic :: Internet :: File Transfer Protocol (FTP)
Requires-Python: >=3.11
License-File: LICENSE
Requires-Dist: alive-progress==3.3.*
Requires-Dist: boto3==1.40.*
Requires-Dist: python-dotenv==1.1.*
Provides-Extra: dev
Requires-Dist: sphinx==5.1.1; extra == "dev"
Requires-Dist: pre-commit; extra == "dev"
Requires-Dist: recommonmark; extra == "dev"
